django_mycli/__init__.py
django_mycli-1.0.1.dist-info/AUTHORS.md
django_mycli-1.0.1.dist-info/LICENSE
django_mycli-1.0.1.dist-info/METADATA
django_mycli-1.0.1.dist-info/WHEEL
django_mycli-1.0.1.dist-info/top_level.txt
django_mycli-1.0.1.dist-info/RECORD
