Metadata-Version: 2.1
Name: django-mycli
Version: 1.0.1
Summary: Database runtime for Django that replaces mysql with mycli.
Home-page: https://github.com/ashchristopher/django-mycli
Author: Ash Christopher
Author-email: ash.christopher@gmail.com
License: BSD
Keywords: django mycli mysql database
Platform: UNKNOWN
Classifier: Development Status :: 5 - Production/Stable
Classifier: Intended Audience :: Developers
Classifier: License :: OSI Approved :: BSD License
Classifier: Natural Language :: English
Classifier: Programming Language :: Python :: 3.5
Classifier: Programming Language :: Python :: 3.6
Classifier: Programming Language :: Python :: 3.7
Classifier: Programming Language :: Python :: 3.8
Requires-Dist: mycli
Requires-Dist: mysqlclient
Requires-Dist: Django (>=2.2)
